Workbook
Name exchange_rate_2011_2010: #REF!
Name Final_demand_residences: '[1]Fuel aggregation'!$L$11
Name hours_a_year: #REF!
Name km2_to_m2: #REF!
Name kW_to_MW: #REF!
Name kW_to_W: #REF!
Name kWp_to_MWp: #REF!
Name m2_to_km2: #REF!
Name STC: #REF!
Name STC_insolation: #REF!
Name W_to_MW: #REF!
Name Wp_to_kWp: #REF!
Name WP_to_MWp: #REF!

Sheet Dashboard
B2: Node | C2: households_water_heater__hybrid_heatpump_air_water_electricity.ad | E2: Description | F2: This sheet summarizes all node attributes formatted in the way they are used by the Energy Transition Model. Use the Excel formulas to find the original data and sources for these numbers. You can also use this document to update the attribute value. Once you have finished updating, save this document and run rake import:node NODE="nodename" to update the node attributes on ETSource. Note: in the final dashboard values, use ROUND to avoid long floats.
B3: Author | C3: Jort Wolda
B4: Organisation | C4: Quintel
C7: Attribute | D7: Unit | E7: Value | G7: Definition | I7: Source
C9: Technical
C10: output.useable_heat.ambient_heat | D10: - | E10: 1 | I10: Quintel assumption
C11: output.useable_heat.electricity | D11: - | E11: 1 | I11: Quintel assumption
C12: output.useable_heat.network_gas | D12: - | E12: =Analysis!D16 -> 0.9 | I12: Quintel assumption
C13: fever.base_cop | D13: - | E13: =Analysis!D19 -> 2.1044 | I13: Bogdanov et al. (2024)
C14: fever.capacity.electricity | D14: MW | E14: =ROUND(Analysis!D35,6) -> 0.001704 | I14: Installatiemonitor 3.0 & Bofdanov et al. (2024)
C15: fever.capacity.network_gas | D15: MW | E15: =ROUND(Analysis!D11,6) -> 0.022 | I15: Based on HR-107 condensing boiler - From households_space_heater_combined_network_gas - Vesta is used as source
C16: fever.cop_cutoff | D16: - | E16: 6 | I16: Quintel assumption (using several sources)
C17: fever.cop_per_degree | D17: - | E17: =ROUND(Analysis!D20,6) -> 0.04074 | I17: Bogdanov et al. (2024)
C18: storage.volume | D18: MWh | E18: 0 | I18: Quintel assumption
C19: availability | D19: - | E19: 0 | I19: Quintel assumption
C20: full_load_hours | D20: - | E20: 0 | I20: Quintel assumption
C21: households_supplied_per_unit | D21: - | E21: 1 | I21: Quintel assumption
C22: heat_output_capacity | D22: MW | E22: =Analysis!D34 -> 0.02354 | G22: Heat output capacity | I22: Installatiemonitor 3.0
C24: Cost
C25: initial_investment | D25: euro | E25: 0 | G25: Initial investment costs | I25: Investment costs are covered at space heating
C26: ccs_investment | D26: euro | E26: 0 | G26: Investment cost with ccs | I26: Investment costs are covered at space heating
C27: cost_of_installing | D27: euro | E27: 0 | G27: Installation cost | I27: Investment costs are covered at space heating
C28: decommissioning_costs | D28: euro | E28: 0 | G28: Decommissioning cost | I28: Investment costs are covered at space heating
C29: fixed_operation_and_maintenance_costs_per_year | D29: euro/year | E29: 0 | G29: Fixed operational and maintenance costs per year | I29: Investment costs are covered at space heating
C30: variable_operation_and_maintenance_costs_per_full_load_hour | D30: euro/FLH | E30: 0 | G30: Variable operational and maintenance costs | I30: Investment costs are covered at space heating
C31: variable_operation_and_maintenance_costs_for_ccs_per_full_load_hour | D31: euro/FLH | E31: 0 | G31: Variable operational and maintenance costs for ccs | I31: Investment costs are covered at space heating
C32: wacc | D32: % | E32: 0.02 | G32: Weighted average cost of capital | I32: Quintel assumption, see https://docs.energytransitionmodel.com/main/cost-wacc/
C33: takes_part_in_ets | D33: yes=1, no=0 | E33: 0 | I33: Quintel assumption
C34: storage.cost_per_mwh | D34: eur0/MWh | E34: 0 | I34: Quintel assumption
C36: Other
C37: construction_time | D37: years | E37: 0 | G37: Construction time of the plant | I37: Quintel assumption
C38: technical_lifetime | D38: years | E38: 15 | G38: Technical lifetime of the plant | I38: Factsheet luchtwarmtepomp
C39: free_co2_factor | D39: - | E39: 0 | I39: Quintel assumption

Sheet Sources
C3: Variables | D3: Title | E3: Author / organisation | F3: Subject country | G3: Published year | H3: Subject year | I3: Retreived year | J3: Link
C4: fever.base_cop, fever.capacity.electricity, fever.cop_per_degree | D4: Installatiemonitor 3.0 - De warmtepomp in de gebouwde omgeving | E4: BDH | F4: NL | G4: 2026 | I4: 2026 | J4: https://kennisdelen.rvo.nl/file/download/a29e1ec4-ad00-4a5b-ba62-287ca7602ddf/Installatiemonitor_3_eindrapportage_v1.02.pdf
C5: technical_lifetime | D5: Factsheet Luchtwarmtepomp | E5: CE Delft | F5: NL | G5: 2021 | I5: 2026 | J5: https://ce.nl/wp-content/uploads/2021/04/04_Factsheet-Luchtwarmtepomp_DEF.pdf
C6: fever.base_cop, fever.cop_per_degree, heat_output_capacity, fever.capacity.electricity | D6: Impact of temperature dependent coefficient of performance of heat pumps on heating systems in national and regional energy systems modelling | E6: Bogdanov, Stymov, Breyer (LUT University) | F6: - | G6: 2024 | I6: 2026 | J6: https://pdf.sciencedirectassets.com/271429/1-s2.0-S0306261924X00148/1-s2.0-S0306261924010304/main.pdf?X-Amz-Security-Token=IQoJb3JpZ2luX2VjEDcaCXVzLWVhc3QtMSJHMEUCIDayx60tWfHNKXVVv8qS6t7aPyy1YM%2BiBAF7FCuifT67AiEAuYqhuC5gy%2FAawde7fGCHiyLrCKGdXwEYRSiojbmpQdMqvAUI%2F%2F%2F%2F%2F%2F%2F%2F%2F%2F%2F%2FARAFGgwwNTkwMDM1NDY4NjUiDOxvvumY1HhRiHczdCqQBRl5ICXGeg74c%2B%2BGt6IdqbTCtLh0Cu69IR5DEAACTsA%2FYwbWrgDr%2BzXwqBDPa6GZ8rgoLiR9YP9HwXG8g%2FsR0yi1Kld1R%2B%2FWY4sYSSMxxVoJmr9SAtWFnzKuv3LwQ0U2Adpceq1YsXSRwmaVFGy7fk389lcW%2Fx0PaB8USbARFUz8p03pCT3wcy8uXWXyCUsRNl6eN2pTmmamMv3RKEWuw3extsuoc3KfxXjb1TvnEDTIgZx1P8BYBcpoGfOuxdPLkVGa8bhbYyZ3HVNKrf7pzMaq17fTLj4PtFdLFyyhuxiXNV3Vv%2BnsdmEbZhPvp99m3lYJsMRX7bHAtXdbw661dYT3M%2BPCe%2B2kJQwMikZxWfs%2FihlZaEbdIlQpMbfX7xST6xM%2BeeEEIvV%2ByABbJ5kxzBBjHzbJtSk%2FN4YhVLoyXDdq1LEenN5CVcFf0YztFQk8SMQoMi%2BAhVpoSV3LUK5DFisHXeXWMHsc3QUDM9XFp26Y1GovhZJ%2FijGUhgTn%2FTC00qogUqGKkhG8ws4pnu94DzqgWxmVjyWX%2FqX30i6fDPpUxSHKujCyTj8siOS1lTNWWz3UoZDFmz3frOI2ztMm%2FVfWe5OVeVblN87IRAYyyxJ5uKCv5C66BGzW4YUiIVBSFkFdv872uvoP5J61SJVs9v20T6SbGfxJM5LLK4KqvQHWYs4YCMzA%2BVEwwXF4hhZ8CVD4PK9cTnxzsdFLLFOkBdrcoYL4uEIaufqbnZthK%2FbpUrMgMYWi2jgW8wG4s9ipCWTg6R5bvu2Ds6Q3UmUo7CglQ%2FJD5ASTEHmqR%2BCGYqUNRAeH4YlHSwliIoR6X77fyWpfWOBygE8rtJa%2FtVr82LfTpIljxYkK79XYmiKV0ls9MPfA%2FNMGOrEBYjfBchqkKUY1si0EA8Zq2hP92hHujyBIqLntJvfEzpLLYb0g37kv5ohpd%2F6qPuxSJ3%2BhVhPJfzDptMtbBx3zUZ4IhdZMgyeZOemV8w1F17hV0fBa03MzuejvBr2JtTLZICTYLwr%2BH0yS3XH9QU13P7vE%2BPpZc5gSh9J9CBi%2FtIddCYJZ1A8g073sJV7VbQyodWrsmfyWIvppurgch2bZZGxtV3uCtxOjTIPHblTrWVX7&X-Amz-Algorithm=AWS4-HMAC-SHA256&X-Amz-Date=20260814T142629Z&X-Amz-SignedHeaders=host&X-Amz-Expires=300&X-Amz-Credential=ASIAQ3PHCVTYQ7GBCDX4%2F20260814%2Fus-east-1%2Fs3%2Faws4_request&X-Amz-Signature=f5505e1ab0c3d216f958b3dd2da6d768b974147a086a958ae13c8ff067f3f793&hash=700ab74877321dbaa56e45a1d6afdbe3b6e32748e211e8ec3c9cab8c75cadcf4&host=68042c943591013ac2b2430a89b270f6af2c76d8dfd086a07176afe7c76c2c61&pii=S0306261924010304&tid=spdf-df67c04d-858b-4d71-8345-3792de26f625&sid=71107c3f109b914cd36b34220ded9018ec04gxrqb&type=client&tsoh=d3d3LnNjaWVuY2VkaXJlY3QuY29t&rh=d3d3LnNjaWVuY2VkaXJlY3QuY29t&ua=140a0653005505515b5757&rr=a2b0a2864a59feb4&cc=nl
C7: fever.base_cop, fever.cop_per_degree | D7: Time series of heat demand and heat pump efficiency for energy system modeling (When2Heat) | E7: Ruhnau, O., Hirth, L. & Praktiknjo, A. | F7: - | G7: 2019 | H7: 2016 | I7: 2026 | J7: https://www.nature.com/articles/s41597-019-0199-y
C8: fever.capacity.electricity | D8: Sinclair SHP-140ICA + SHP-140ECA product fiche | E8: Sinclair | F8: - | G8: - | H8: - | I8: - | J8: https://www.sinclair-solutions.com/files/product-fiche/sinclair-prfi-shp-140ica-shp-140eca2.pdf
C9: fever.base_cop, fever.cop_per_degree | D9: WARM TAPWATERINSTALLATIES Leidingontwerp, wachttijden, toestellen en temperatuurregeling | E9: Samenwerkende Drinkwaterbedrijven | F9: NL | G9: 2023 | H9: - | I9: 2026 | J9: https://www.infodwi.nl/media/50phiyot/concept-waterwerkblad-4-4a-december-2023_1.pdf
C10: fever.base_cop, fever.cop_per_degree | D10: Klimaatdashboard | E10: KNMI | F10: - | G10: - | H10: - | I10: 2026 | J10: https://www.knmi.nl/klimaat#klimaatdashboard
C26: Note: "published year" might deviate from "subject year". For example, a study can be published in 2024 about costs parameters in 2020.

Sheet Analysis
C3: variable | D3: value | E3: unit | F3: comment | G3: source | M3: Screenshots
C5: technical_lifetime | D5: 15 | E5: years | G5: Main source: | H5: Factsheet warmtepompen
C11: fever.capacity.network_gas | D11: 0.022 | E11: MW | F11: Same assumptions as used in households_space_heater_combined_network_gas.converter.ad
F13: Covered more extensively there
F14: In general, capacity for central heating boilers are mostly related to the peak demand caused by tap water. So it makes sense to have the same value for here as tap water is coverd by the gas boiler.
C16: output.useable_heat.network_gas | D16: 0.9 | F16: From households_water_heater_combined_network_gas
F17: Efficiency is lower compared to the 107% that is used for space heating using network gas. The main difference is that because of higher temperature, the condensation doesn't occur.
C19: fever.base_cop | D19: =AL32 -> 2.1044 | F19: Bogdanov et al. (2024) give COP formulas as a function of delta T for air, ground and water source heat pumps. The formulas originate from Ruhnau et al. (2019), which used 2016 manufacturer data, but Bogdanov et al. updated the coefficients. The changes are small but the fact they're refised in 2024 improves credibility. While the formula has an exponential term, the curve is nearly linear in the relevant range (see chart). These attributes should reproduce a SCOP broadly in line with the static value under typical conditions. Tap water installations have to heat up to at least 55 °C at the tap, which means the temperature at the tank must be slightly higher, at least. So, we'll use an estimated average of 60 °C. Combined with average outside temperature of ~10 °C a COP of 2.5 is found using the formula. Close to installatiemonitor values. The COP per degree is derived from the average step between −10 and 15 °C outside temperature. | G19: Main source: | H19: Bogdanov et al. (2024)
C20: fever.cop_per_degree | D20: =AK49 -> 0.04074 | G20: Supporting source: | H20: Ruhnau et al. (2019) | AH20: Test formule (ASHP)
G21: Supporting source: | H21: Samenwerkende Drinkwaterbedrijven | AH21: Outside temp | AI21: Sink temp | AJ21: delta T | AK21: COP | AL21: COP (lineair aproximation)
G22: Supporting source: | H22: KNMI klimaatdashboard | AH22: -10 | AI22: 60 | AJ22: =AI22-AH22 -> 70 | AK22: =6.08 - 0.0941 * AJ22 + 0.000464 * AJ22^2 -> 1.7666 | AL22: =AL23-$AK$49 -> 1.697
AH23: =AH22+1 -> -9 | AI23: 60 | AJ23: =AI23-AH23 -> 69 | AK23: =6.08 - 0.0941 * AJ23 + 0.000464 * AJ23^2 -> 1.796204 | AL23: =AL24-$AK$49 -> 1.73774
AH24: =AH23+1 -> -8 | AI24: 60 | AJ24: =AI24-AH24 -> 68 | AK24: =6.08 - 0.0941 * AJ24 + 0.000464 * AJ24^2 -> 1.826736 | AL24: =AL25-$AK$49 -> 1.77848
AH25: =AH24+1 -> -7 | AI25: 60 | AJ25: =AI25-AH25 -> 67 | AK25: =6.08 - 0.0941 * AJ25 + 0.000464 * AJ25^2 -> 1.858196 | AL25: =AL26-$AK$49 -> 1.81922
AH26: =AH25+1 -> -6 | AI26: 60 | AJ26: =AI26-AH26 -> 66 | AK26: =6.08 - 0.0941 * AJ26 + 0.000464 * AJ26^2 -> 1.890584 | AL26: =AL27-$AK$49 -> 1.85996
AH27: =AH26+1 -> -5 | AI27: 60 | AJ27: =AI27-AH27 -> 65 | AK27: =6.08 - 0.0941 * AJ27 + 0.000464 * AJ27^2 -> 1.9239 | AL27: =AL28-$AK$49 -> 1.9007
AH28: =AH27+1 -> -4 | AI28: 60 | AJ28: =AI28-AH28 -> 64 | AK28: =6.08 - 0.0941 * AJ28 + 0.000464 * AJ28^2 -> 1.958144 | AL28: =AL29-$AK$49 -> 1.94144
AH29: =AH28+1 -> -3 | AI29: 60 | AJ29: =AI29-AH29 -> 63 | AK29: =6.08 - 0.0941 * AJ29 + 0.000464 * AJ29^2 -> 1.993316 | AL29: =AL30-$AK$49 -> 1.98218
AH30: =AH29+1 -> -2 | AI30: 60 | AJ30: =AI30-AH30 -> 62 | AK30: =6.08 - 0.0941 * AJ30 + 0.000464 * AJ30^2 -> 2.029416 | AL30: =AL31-$AK$49 -> 2.02292
AH31: =AH30+1 -> -1 | AI31: 60 | AJ31: =AI31-AH31 -> 61 | AK31: =6.08 - 0.0941 * AJ31 + 0.000464 * AJ31^2 -> 2.066444 | AL31: =AL32-$AK$49 -> 2.06366
AG32: Base COP | AH32: =AH31+1 -> 0 | AI32: 60 | AJ32: =AI32-AH32 -> 60 | AK32: =6.08 - 0.0941 * AJ32 + 0.000464 * AJ32^2 -> 2.1044 | AL32: =AK32 -> 2.1044
AH33: =AH32+1 -> 1 | AI33: 60 | AJ33: =AI33-AH33 -> 59 | AK33: =6.08 - 0.0941 * AJ33 + 0.000464 * AJ33^2 -> 2.143284 | AL33: =AL32+$AK$49 -> 2.14514
C34: heat_output_capacity | D34: =D11*1.07 -> 0.02354 | E34: MW | F34: The average bivalence capacity* of hybrid heat pumps in the Installatiemonitor research was 4.6 kW. The COP at bivalence capacity according to Bogdanov et al. (2024) is 2.7. Which is used to find the electrical capacity. In practice either the gas boiler or the heat pump runs, not both at the same time. Therefore the heat_output_capacity is calculated based on the highest capacity of the two is used. The heat_output_capacity is aligned with the heat_output_capacity of the space heater. Therefore an efficiency of 1.07 is used instead of 0.90 *The capacity of the heat pump at the lowest outdoor temperature point at which the heat pump is declared to have a capacity able to meet 100 % of the heating load without supplementary heater This temperature is often around -7 °C as for the Sinclair SHP-140ICA + SHP-140ECA | G34: Main source: | H34: Installatiemonitor 3.0 | AH34: =AH33+1 -> 2 | AI34: 60 | AJ34: =AI34-AH34 -> 58 | AK34: =6.08 - 0.0941 * AJ34 + 0.000464 * AJ34^2 -> 2.183096 | AL34: =AL33+$AK$49 -> 2.18588
C35: fever.capacity.electricity | D35: =0.0046/2.7 -> 0.0017037037 | E35: MW | G35: Supporting source: | H35: Bogdanov et al. (2024) | AH35: =AH34+1 -> 3 | AI35: 60 | AJ35: =AI35-AH35 -> 57 | AK35: =6.08 - 0.0941 * AJ35 + 0.000464 * AJ35^2 -> 2.223836 | AL35: =AL34+$AK$49 -> 2.22662
G36: Supporting source: | H36: Sinclair | AH36: =AH35+1 -> 4 | AI36: 60 | AJ36: =AI36-AH36 -> 56 | AK36: =6.08 - 0.0941 * AJ36 + 0.000464 * AJ36^2 -> 2.265504 | AL36: =AL35+$AK$49 -> 2.26736
AH37: =AH36+1 -> 5 | AI37: 60 | AJ37: =AI37-AH37 -> 55 | AK37: =6.08 - 0.0941 * AJ37 + 0.000464 * AJ37^2 -> 2.3081 | AL37: =AL36+$AK$49 -> 2.3081
AH38: =AH37+1 -> 6 | AI38: 60 | AJ38: =AI38-AH38 -> 54 | AK38: =6.08 - 0.0941 * AJ38 + 0.000464 * AJ38^2 -> 2.351624 | AL38: =AL37+$AK$49 -> 2.34884
AH39: =AH38+1 -> 7 | AI39: 60 | AJ39: =AI39-AH39 -> 53 | AK39: =6.08 - 0.0941 * AJ39 + 0.000464 * AJ39^2 -> 2.396076 | AL39: =AL38+$AK$49 -> 2.38958
AH40: =AH39+1 -> 8 | AI40: 60 | AJ40: =AI40-AH40 -> 52 | AK40: =6.08 - 0.0941 * AJ40 + 0.000464 * AJ40^2 -> 2.441456 | AL40: =AL39+$AK$49 -> 2.43032
AH41: =AH40+1 -> 9 | AI41: 60 | AJ41: =AI41-AH41 -> 51 | AK41: =6.08 - 0.0941 * AJ41 + 0.000464 * AJ41^2 -> 2.487764 | AL41: =AL40+$AK$49 -> 2.47106
AH42: =AH41+1 -> 10 | AI42: 60 | AJ42: =AI42-AH42 -> 50 | AK42: =6.08 - 0.0941 * AJ42 + 0.000464 * AJ42^2 -> 2.535 | AL42: =AL41+$AK$49 -> 2.5118
AH43: =AH42+1 -> 11 | AI43: 60 | AJ43: =AI43-AH43 -> 49 | AK43: =6.08 - 0.0941 * AJ43 + 0.000464 * AJ43^2 -> 2.583164 | AL43: =AL42+$AK$49 -> 2.55254
AH44: =AH43+1 -> 12 | AI44: 60 | AJ44: =AI44-AH44 -> 48 | AK44: =6.08 - 0.0941 * AJ44 + 0.000464 * AJ44^2 -> 2.632256 | AL44: =AL43+$AK$49 -> 2.59328
AH45: =AH44+1 -> 13 | AI45: 60 | AJ45: =AI45-AH45 -> 47 | AK45: =6.08 - 0.0941 * AJ45 + 0.000464 * AJ45^2 -> 2.682276 | AL45: =AL44+$AK$49 -> 2.63402
AH46: =AH45+1 -> 14 | AI46: 60 | AJ46: =AI46-AH46 -> 46 | AK46: =6.08 - 0.0941 * AJ46 + 0.000464 * AJ46^2 -> 2.733224 | AL46: =AL45+$AK$49 -> 2.67476
AH47: =AH46+1 -> 15 | AI47: 60 | AJ47: =AI47-AH47 -> 45 | AK47: =6.08 - 0.0941 * AJ47 + 0.000464 * AJ47^2 -> 2.7851 | AL47: =AL46+$AK$49 -> 2.7155
AH49: Average COP per degree | AK49: =(AK47-AK22)/(AH47-AH22) -> 0.04074
