Workbook
Name exchange_rate_2011_2010: #REF!
Name Final_demand_residences: '[1]Fuel aggregation'!$L$11
Name hours_a_year: #REF!
Name km2_to_m2: #REF!
Name kW_to_MW: #REF!
Name kW_to_W: #REF!
Name kWp_to_MWp: #REF!
Name m2_to_km2: #REF!
Name STC: #REF!
Name STC_insolation: #REF!
Name W_to_MW: #REF!
Name Wp_to_kWp: #REF!
Name WP_to_MWp: #REF!

Sheet Cover sheet
B2: Cover Sheet
B4: Document | C4: transport_bus_using_electricity.converter.ad
B5: Author | C5: Robin de Smit
B6: Organization | C6: Quintel Intelligence
B9: Legend
B11: Cells | C11: Intermediate (calculation)
C12: Result
C13: Manual input
C14: Reference to manual input or data input
B16: Tabs | C16: Introductory
C17: Dashboard
C18: Research data
C19: Sources
C20: Results
C21: Main calculations
C22: Additional calculations
C23: Output to csv

Sheet Dashboard
B2: This sheet summarizes all node attributes formatted in the way they are used by the Energy Transition Model. Use the Excel formulas to find the original data and sources for these numbers. You can also use this document to update the attribute value. Once you have finished updating, save this document and run rake import:node NODE="nodename" to update the node attributes on ETSource.
C8: Attribute | D8: Unit | E8: Value | G8: Definition | I8: Source
C10: Technical
C11: output.passenger_kms | D11: pkm/MJ | E11: ='Research data'!E7 -> 1.763043 | I11: CE Delft
C12: storage.volume | D12: MWh | E12: ='Research data'!E8 -> 0.216 | I12: VDL
C13: storage.decay | D13: % per hour | E13: ='Research data'!E9 -> 5.4866767e-05 | I13: Tesla
C14: electricity_output_capacity | D14: MW | E14: ='Research data'!E10 -> 0.32 | I14: VDL
C15: typical_input_capacity | D15: MW | E15: ='Research data'!E11 -> 0.32 | I15: VDL
C16: availability | D16: - | E16: 1 | I16: Quintel assumption
C17: full_load_hours | D17: - | E17: 0 | I17: Necessary attribute for 0 euro costs baseline
C19: Cost
C20: initial_investment | D20: euro | E20: 0 | G20: Initial investment costs | I20: The ETM only encompasses costs that are directly related to the energy system, see documentation: https://docs.energytransitionmodel.com/main/cost-main-principles
C21: fixed_operation_and_maintenance_costs_per_year | D21: euro/year | E21: 0 | G21: Fixed operational and maintenance costs per year | I21: The ETM only encompasses costs that are directly related to the energy system, see documentation: https://docs.energytransitionmodel.com/main/cost-main-principles
C22: ccs_investment | E22: 0 | G22: CCS investment costs | I22: The ETM only encompasses costs that are directly related to the energy system, see documentation: https://docs.energytransitionmodel.com/main/cost-main-principles
C23: cost_of_installing | E23: 0 | G23: Installation costs | I23: The ETM only encompasses costs that are directly related to the energy system, see documentation: https://docs.energytransitionmodel.com/main/cost-main-principles
C24: decommissioning_costs | E24: 0 | G24: Decommissioning costs | I24: The ETM only encompasses costs that are directly related to the energy system, see documentation: https://docs.energytransitionmodel.com/main/cost-main-principles
C25: variable_operation_and_maintenance_costs_per_full_load_hour | E25: 0 | G25: Variable operational and maintenance costs per flh | I25: The ETM only encompasses costs that are directly related to the energy system, see documentation: https://docs.energytransitionmodel.com/main/cost-main-principles
C26: variable_operation_and_maintenance_costs_for_ccs_per_full_load_hour | E26: 0 | G26: Variable operational and maintenance costs for ccs per flh | I26: The ETM only encompasses costs that are directly related to the energy system, see documentation: https://docs.energytransitionmodel.com/main/cost-main-principles
C27: wacc | D27: % | E27: 0.04 | G27: Weighted average cost of capital | I27: Quintel assumption (see https://docs.energytransitionmodel.com/main/cost-wacc)
C28: takes_part_in_ets | D28: yes=1, no=0 | E28: 0 | I28: Does not take part in ETS
C30: Other
C31: technical_lifetime | D31: years | E31: ='Research data'!E14 -> 14 | G31: Technical lifetime | I31: cedelft-ecn-tno
C32: construction_time | D32: years | E32: 0 | G32: Construction time of the plant | I32: Set to 0 baseline
C33: free_co2_factor | D33: - | E33: 0 | I33: Quintel assumption

Sheet Research data
C4: Parameter | D4: Unit | E4: Results | H4: cedelft-ecn-tno | I4: VDL | J4: Tesla | K4: CE Delft | L4: Comments
C6: Technical
C7: output.passenger_kms | D7: pkm/MJ | E7: =K7 -> 1.763043 | K7: =Notes!E17 -> 1.763043
C8: storage.volume | D8: MWh | E8: =I8 -> 0.216 | I8: =Notes!E108 -> 0.216
C9: storage.decay | D9: % per hour | E9: =J9 -> 5.4866767e-05 | J9: =Notes!E132 -> 5.4866767e-05
C10: electricity_output_capacity | D10: MW | E10: =I10 -> 0.32 | I10: =Notes!E111 -> 0.32
C11: typical_input_capacity | D11: MW | E11: =I11 -> 0.32 | I11: =Notes!E110 -> 0.32
C13: Other
C14: technical_lifetime | D14: years | E14: =H14 -> 14 | H14: =Notes!C89 -> 14

Sheet Sources
C3: Definition on the sources
C5: Type | D5: Source | E5: Country | F5: Date published | G5: Subject year | H5: Date retrieved | I5: ETM Library URL | J5: Link
C6: Efficiency | D6: CE Delft | E6: NL | F6: 2024 | G6: 2024 | H6: 2026 | J6: https://ce.nl/wp-content/uploads/2025/02/CE_Delft_210506_STREAM_Personenvervoer_2024_Def.pdf
C7: Initial investment costs
C8: Technical lifetime
C9: passenger km/vehicle km | D9: CE Delft | E9: NL | F9: 2024 | G9: 2024 | H9: 2026 | J9: https://ce.nl/wp-content/uploads/2025/02/CE_Delft_210506_STREAM_Personenvervoer_2024_Def.pdf
C13: storage.decay | D13: Tesla model s owner's manual | E13: EU | F13: 2013 | G13: 2013 | H13: 23/08/16 | J13: https://www.tesla.com/sites/default/files/blog_attachments/model_s_owners_manual_europe_1.0.pdf
C15: storage.volume | D15: VDL Citea brochure | E15: NL | F15: 2019 | G15: 2019 | H15: 01/2023 | I15: https://brochures.vdlbuscoach.com/en/brochure.html?brochure=3&lang=83
C16: typical_input_capacity
C17: electricity_output_capacity

Sheet Notes
C3: Sources | D3: Notes
C11: CE Delft (2024) | E11: 4.6 | F11: MJ/km
C12: p. 39 | E12: =1/E11 -> 0.2173913 | F12: km/MJ
C14: CE Delft (2024) | E14: 8.11 | F14: passenger km/vehicle km
C15: p. 18
D17: =Dashboard!C11 -> output.passenger_kms | E17: =ROUND(E14*E12, 6) -> 1.763043 | F17: passenger km/MJ
C83: cedelft-ecn-tno
C84: p.87
C89: 14 | D89: yr
C103: VDL Citea busses
C104: p.23
D107: storage.volume | E107: 216 | F107: kWh
E108: =E107/1000 -> 0.216 | F108: MWh
D109: typical_input_capacity | E109: 320 | F109: kW
E110: =E109/1000 -> 0.32 | F110: MW
D111: electricity_output_capacity | E111: =E110 -> 0.32 | F111: MW | G111: assumption: input capacity = output capacity
C127: Tesla model s owner's manual
C128: p 6.4
C129: Decay assumed to be the same as for lithium-ion battteries in cars as decay depends on battery type, not vehicle
D131: storage decay per month | E131: 0.04
D132: storage decay per hour | E132: =1-(1-E131)^(1/(24*31)) -> 5.4866767e-05
