Workbook
Name exchange_rate_2011_2010: #REF!
Name Final_demand_residences: '[1]Fuel aggregation'!$L$11
Name hours_a_year: #REF!
Name km2_to_m2: #REF!
Name kW_to_MW: #REF!
Name kW_to_W: #REF!
Name kWp_to_MWp: #REF!
Name m2_to_km2: #REF!
Name STC: #REF!
Name STC_insolation: #REF!
Name W_to_MW: #REF!
Name Wp_to_kWp: #REF!
Name WP_to_MWp: #REF!

Sheet Cover sheet
B2: Cover Sheet
B4: Document | C4: energy_chp_combined_cycle_mt_hydrogen.ad
B5: Duplicate of | C5: energy_chp_combined_cycle_mt_network_gas.ad
B6: Author | C6: Robin de Smit
B7: Organization | C7: Quintel Intelligence
B10: Legend
B12: Cells | C12: Intermediate (calculation)
C13: Result
C14: Manual input
C15: Reference to manual input or data input
B17: Tabs | C17: Introductory
C18: Dashboard
C19: Research data
C20: Sources
C21: Results
C22: Main calculations
C23: Additional calculations
C24: Output to csv

Sheet Dashboard
B2: This sheet summarizes all node attributes formatted in the way they are used by the Energy Transition Model. Use the Excel formulas to find the original data and sources for these numbers. You can also use this document to update the attribute value. Once you have finished updating, save this document and run rake import:node NODE="nodename" to update the node attributes on ETSource.
C7: Attribute | D7: Unit | E7: Value | G7: Definition | I7: Source
C9: Technical
C10: availability | D10: - | E10: 0.9 | I10: quintel/etsource@0277ad226491f5aae44c874b298cbcf694d2f6cb
C11: typical_input_capacity | D11: MW | E11: ='Research data'!G8 -> 260.9 | G11: Input capacity | I11: Energymatters
C13: Cost
C14: initial_investment | D14: euro | E14: ='Research data'!G17 -> 144900000 | G14: Initial investment costs | I14: Energymatters, Öberg (2022)
C15: ccs_investment | D15: euro | E15: 0 | G15: Investment cost with ccs | I15: quintel/etsource@0277ad226491f5aae44c874b298cbcf694d2f6cb
C16: cost_of_installing | D16: euro | E16: 0 | G16: Installation cost | I16: quintel/etsource@0277ad226491f5aae44c874b298cbcf694d2f6cb
C17: decommissioning_costs | D17: eur | E17: 0 | G17: Decmmmissioning cost | I17: quintel/etsource@0277ad226491f5aae44c874b298cbcf694d2f6cb
C18: fixed_operation_and_maintenance_costs_per_year | D18: euro/year | E18: ='Research data'!G20 -> 1095652.2 | G18: Fixed operational and maintenance costs per year | I18: https://github.com/quintel/etsource/issues/272#issuecomment-17880519
C19: variable_operation_and_maintenance_costs_per_full_load_hour | D19: euro/FLH | E19: ='Research data'!G23 -> 328.7 | G19: Variable operational and maintenance costs | I19: https://github.com/quintel/etsource/issues/272#issuecomment-17880519
C20: variable_operation_and_maintenance_costs_for_ccs_per_full_load_hour | D20: euro/FLH | E20: 0 | G20: Variable operational and maintenance costs for ccs | I20: quintel/etsource@0277ad226491f5aae44c874b298cbcf694d2f6cb
C21: wacc | D21: % | E21: 0.07 | G21: Weighted average cost of capita | I21: See https://github.com/quintel/documentation/blob/master/general/cost_calculations.md#weighted-average-cost-of-capital
C22: takes_part_in_ets | D22: yes=1, no=0 | E22: 1 | I22: quintel/etsource@0277ad226491f5aae44c874b298cbcf694d2f6cb
C24: Other
C25: construction_time | D25: years | E25: ='Research data'!G13 -> 2.5 | G25: Construction time of the plant | I25: iea-etsap
C26: technical_lifetime | D26: years | E26: ='Research data'!G14 -> 30 | G26: Technical lifetime of the plant | I26: iea-etsap
C27: free_co2_factor | D27: - | E27: 0 | I27: quintel/etsource@0277ad226491f5aae44c874b298cbcf694d2f6cb

Sheet Research data
C3: Parameter | F3: Unit | G3: Results | I3: Energymatters | K3: Ecofys | M3: iea-etsap | O3: Moerdijk | Q3: Comments
C5: Technical
C6: output.electricity | G6: =K6 -> 0.46 | K6: =Notes!D98 -> 0.46
C7: output.steam_hot_water | G7: =K7 -> 0.42 | K7: =Notes!D99 -> 0.42
C8: typical_input_capacity | G8: =ROUND(G9/K6,1) -> 260.9
C9: electricity_output_capacity | F9: MW | G9: =I9 -> 120 | I9: =Notes!D28 -> 120
C10: heat_output_capacity | F10: MW | G10: =I10 -> 109.56522 | I10: =Notes!D101 -> 109.56522
C12: Other
C13: Construction time | F13: years | G13: =ROUND(2.5,1) -> 2.5 | M13: =Notes!D84/12 -> 2.5
C14: Technical lifetime | F14: years | G14: =ROUND(30,0) -> 30 | M14: =Notes!D85 -> 30
C16: Costs
C17: Initial investment costs | F17: euro | G17: =ROUND(G18*G9*1000,2) -> 144900000
C18: Initial investment costs per Kwe | F18: euro/Kwe | G18: =ROUND(Notes!D46,6) -> 1207.5 | I18: =Notes!D46 -> 1207.5 | K18: =Notes!D116 -> 1150 | Q18: Data from Energymatters report is used with correction of the ratio hydrogen to network gas as described in Öberg (2022).
C19: Total fixed operational and maintenance costs | F19: euro | G19: =G20+G22 -> 2574802.2 | I19: =Notes!$D$71 -> 2520000
C20: Fixed operational and maintenance costs | F20: euro | G20: =ROUND(G21*G10*1000,2) -> 1095652.2 | Q20: The calculations for fixed and variable operating and maintenance costs are described in detail in:
C21: Fixed operational and maintenance costs | F21: euro/KW/year | G21: 10 | Q21: GitHub Ticket
C22: Variable operational and maintenance costs | F22: euro | G22: =G23*G25 -> 1479150 | Q22: The fixed O&M cost : 1/3 of the total operational and maintenance costs
C23: Variable operational and maintenance costs | F23: euro/FLH | G23: =ROUND(G24*G26/G25,2) -> 328.7 | Q23: The variable O&M cost : 2/3 of the total operational and maintenance costs
C24: Variable operational and maintenance costs | F24: euro/MWh | G24: 3 | I24: =Notes!D72 -> 3.5 | K24: =Notes!D110 -> 3 | Q24: The ratio of fixed and variable O&M costs is recommended by an expert from Energymatters.
C25: Full load hours | F25: FLH | G25: 4500 | Q25: The variable O&M cost for "energy_chp_combined_cycle_gas" plant are slightly higher than the "energy_power_combined_cycle_gas" plant, the fixed O&M has remaines the same
C26: Production Electricity yearly | F26: MWh/year | G26: =G25*G10 -> 493043.48 | Q26: The total O&M cost is slighty higher than the Energymatters report.
Q27: It is assumed 3 euro/MWh for variable O&M cost and the rest is allocated for fixed O&M cost.
Q28: The ratio of fixed and variable O&M costs is close to 1/3 for fixed and 2/3 for variable O&M cost in order to be consistent with the "energy_power_combined_cycle_gas" plant.

Sheet Sources
C3: Definition on the sources
C5: Type | E5: Source | F5: Country | G5: Date published | H5: Subject year | I5: Date retrived | J5: ETM Library URL | K5: Link
E7: Energymatters | F7: NL | G7: 2012 | H7: 2012 | J7: http://refman.et-model.com/publications/1937
C8: Investment cost
C9: Total operational and maintenance cost
E11: iea-etsap | F11: EU | G11: 2010 | H11: 2009 | J11: http://refman.et-model.com/publications/1960 | K11: http://www.iea-etsap.org/web/e-techds/pdf/e02-gas_fired_power-gs-ad-gct.pdf
C12: Construction time
C13: Technical lifetime
E15: Ecofys | F15: EU | G15: 2014 | H15: 2014 | J15: http://refman.et-model.com/publications/1943 | K15: http://www.ecofys.com/files/files/ecofys-eci-2014-flexibility-options-in-electricity-systems.pdf
C16: Investment cost
C17: Variable operational and maintenance costs
E18: Öberg, S., Odenberger, M., & Johnsson, F. (2022)
C19: Ratio investment cost hydrogen to network gas | F19: US | G19: 2022 | I19: 2026 | J19: https://www.sciencedirect.com/science/article/pii/S0360319921039768
E21: GitHub | G21: 2013 | K21: https://github.com/quintel/etsource/issues/272#issuecomment-17880519
C22: Fixed operational and maintenance costs
C23: Variable operational and maintenance costs

Sheet Notes
C3: Source | D3: Notes
C5: As hydrogen-fired CCGT CHP is still an emerging technology, detailed technological and financial specifications are not yet available.
C6: Based on expert consultation from BlueTerra, the technological specifications from the hydrogen-fired variant will not deviate significantly from the gas variant.
C7: Therefore, the same technological specs are used for the hydrogen-fired variant with exeption of the investment costs.
C12: Energymatters
C13: p.1
C27: electricity_output_capacity | D27: 120000 | E27: KWe
D28: =D27/1000 -> 120 | E28: MWe
D29: 1050 | E29: euro/KWe
C42: ratio investment cost | D42: 1.15 | E42: hydrogen compared
E43: to network gas
C46: initial investment cost per KW | D46: =D29*D42 -> 1207.5 | E46: euro/KW
C55: p.5
D71: 2520000 | E71: euro/yr
C72: Variable O&M | D72: 3.5 | E72: euro/MWh
C77: iea-etsap
C78: p.4
D84: 30 | E84: months
D85: 30 | E85: yr
C93: Ecofys
C94: p.17
C97: Efficiency CCGT CHP
C98: output.electricity | D98: 0.46
C99: output.steam_hot_water | D99: 0.42
C101: heat_output_capacity | D101: =(D28/D98)*D99 -> 109.56522 | E101: MW
C109: Initial investment for network gas | D109: 1000 | E109: euro/KW
C110: Vriable O&M | D110: 3 | E110: euro/MWh
C116: Initial investment for hydrogen | D116: =D109*D42 -> 1150 | E116: euro/KW
