Workbook
Name exchange_rate_2011_2010: #REF!
Name Final_demand_residences: '[1]Fuel aggregation'!$L$11
Name hours_a_year: #REF!
Name km2_to_m2: #REF!
Name kW_to_MW: #REF!
Name kW_to_W: #REF!
Name kWp_to_MWp: #REF!
Name labor_cost: Notes!#REF!
Name licensing: Notes!#REF!
Name m2_to_km2: #REF!
Name overhead_GA: Notes!#REF!
Name sensitivity_07: '[2]Tornado Charts'!$I$48
Name STC: #REF!
Name STC_insolation: #REF!
Name tax_insurance: Notes!#REF!
Name W_to_MW: #REF!
Name Wp_to_kWp: #REF!
Name WP_to_MWp: #REF!

Sheet Cover sheet
B2: Cover Sheet
B4: Document | C4: energy_production_fischer_tropsch_biogenic_waste_ccs
B5: Author | C5: Kyra de Haan
B6: Organization | C6: Quintel
B9: Legend
B11: Cells | C11: Intermediate (calculation)
C12: Result
C13: Manual input
C14: Reference to manual input or data input
B16: Tabs | C16: Introductory
C17: Dashboard
C18: Research data
C19: Sources
C20: Results
C21: Main calculations
C22: Additional calculations
C23: Output to csv

Sheet Dashboard
B2: This sheet summarizes all node attributes formatted in the way they are used by the Energy Transition Model. Use the Excel formulas to find the original data and sources for these numbers. You can also use this document to update the attribute value. Once you have finished updating, save this document and run rake import:node NODE="nodename" to update the node attributes on ETSource.
C9: Attribute | D9: Unit | E9: Value | G9: Definition | I9: Source
C11: Technical
C12: typical_input_capacity | D12: MW | E12: =ROUND(Notes!D6,3) -> 370.708 | I12: Danish Energy Agency
C13: input.biogenic_waste | D13: - | E13: =ROUND(Notes!D21,5) -> 1 | I13: Danish Energy Agency
C14: output.bio_kerosene | D14: - | E14: =ROUND(Notes!D17,5) -> 0.15474 | I14: Danish Energy Agency
C15: output.biodiesel | D15: - | E15: =ROUND(Notes!D18,5) -> 0.10505 | I15: Danish Energy Agency
C16: output.bionaphtha | D16: - | E16: =ROUND(Notes!D19,5) -> 0.14484 | I16: Danish Energy Agency
C17: full_load_hours | D17: h | E17: =Notes!D7 -> 8000 | I17: Danish Energy Agency
C18: availability | D18: - | E18: =ROUND(Notes!D10,3) -> 0.962
C20: Cost
C21: initial_investment | D21: euro | E21: =ROUND(Notes!D12,0) -> 584415584 | G21: Initial investment costs | I21: Danish Energy Agency
C22: ccs_investment | D22: euro | E22: =ROUND(Notes!D24,0) -> 67820558 | I22: taken from energy_hydrogen_biomass_gasification_ccs
C23: fixed_operation_and_maintenance_costs_per_year | D23: euro/yr | E23: =ROUND(Notes!D13,0) -> 15584416 | G23: Fixed operational and maintenance costs per year (incl. ccs) | I23: Danish Energy Agency
C24: variable_operation_and_maintenance_costs_per_full_load_hour | D24: euro/flh | E24: =ROUND(Notes!D14,2) -> 162.34 | G24: Variable operation and maintenance costs per flh | I24: Danish Energy Agency
C25: variable_operation_and_maintenance_costs_for_ccs_per_full_load_hour | D25: euro/flh | E25: =Notes!D25 -> 0 | I25: taken from energy_hydrogen_biomass_gasification_ccs
C26: cost_of_installing | D26: euro | E26: 0 | G26: Installation costs | I26: No data available, assumed to be part of initial investment
C27: decommissioning_costs | D27: euro | E27: 0 | G27: Decommissioning costs | I27: No data available, assumed to be part of initial investment
C28: wacc | D28: % | E28: 0.07 | G28: Weighted average cost of capita | I28: See https://docs.energytransitionmodel.com/main/cost-wacc/
C29: takes_part_in_ets | D29: yes=1, no=0 | E29: 1 | I29: Quintel assumption
C31: Other
C32: technical_lifetime | D32: years | E32: =Notes!D8 -> 25 | G32: Technical lifetime of the plant | I32: Danish Energy Agency
C33: construction_time | D33: years | E33: =Notes!D9 -> 2 | G33: Construction time of the plant | I33: Danish Energy Agency
C34: free_co2_factor | D34: - | E34: =Notes!D94 -> 0.632781 | I34: Calculated using carbon balance
C35: ccs_capture_rate | D35: - | E35: =Notes!D95 -> 0.9 | I35: Taken from energy_hydrogen_biomass_gasification_ccs

Sheet Sources
C3: Definition on the sources
C5: Type | D5: Source | E5: Country | F5: Date published | G5: Subject | H5: Date retrieved | I5: ETM Library URL | J5: Link
B7: Biomass gassification & Fischer Tropsch | C7: All specs | D7: Danish Energy Agency | E7: DK | F7: 2025 | G7: Renewable fuels: Technology descriptions and projections for long-term energy system planning | H7: 45887 | I7: https://refman.energytransitionmodel.com/publications/2218
C8: All specs | D8: Danish Energy Agency | E8: DK | F8: 2025 | G8: Data Sheets for energy carrier generation and conversion | H8: 45887 | I8: https://refman.energytransitionmodel.com/publications/2219

Sheet Notes
C3: Source | D3: Page | E3: Notes
C5: Overview | K5: Jet fuel from biomass gasification, table from DEA:
C6: Input capacity | D6: =D43/(1-E34) -> 370.7076 | E6: MW
C7: Full load hours | D7: =D44 -> 8000 | E7: hours
C8: Technical lifetime | D8: =D45 -> 25 | E8: y | K8: year | M8: 2015 | N8: 2020 | O8: 2030 | P8: 2040 | Q8: 2050 | R8: 2020 | S8: 2020 | T8: 2050 | U8: 2050 | V8: Note | W8: Ref
C9: Construciton period | D9: =D46 -> 2 | E9: y | K9: est | M9: ctrl | N9: ctrl | O9: ctrl | P9: ctrl | Q9: ctrl | R9: Lower | S9: Upper | T9: Lower | U9: Upper | V9: - | W9: -
C10: availability | D10: =1-(N21/52) -> 0.96153846 | K10: Energy/technical data
L11: Typical total plant size [1,000 t FT Liquids/year] | M11: 50 | N11: 50 | O11: 100 | P11: 125 | Q11: 150 | R11: 1 | S11: 1.5 | T11: 0.5 | U11: 1.5 | V11: A, B | W11: 1, 6
C12: Investment | D12: =D49 -> 5.8441558e+08 | E12: euro | L12: Typical total plant size [MW] | M12: 75 | N12: 75 | O12: 150 | P12: 190 | Q12: 225 | R12: 1 | S12: 1.5 | T12: 0.5 | U12: 1.5 | V12: A, A1, B | W12: 1, 6
C13: Fixed O&M | D13: =D50 -> 15584416 | E13: euro/y | L13: Input
C14: Variable O&M | D14: =D52 -> 162.33766 | E14: euro/flh | L14: Feedstock Consumption [MWh/MWh Total Input] | M14: 1 | N14: 1 | O14: 1 | P14: 1 | Q14: 1 | R14: 0.8 | S14: 1 | T14: 0.8 | U14: 1 | V14: C | W14: 1
L15: Output
C16: Input/output | L16: Naphta Output [MWh/MWh Total Input] | M16: 0.1376 | N16: 0.1376 | O16: =N16*0.4/0.38 -> 0.14484211 | P16: =(O16+Q16)/2 -> 0.15389474 | Q16: =N16*0.45/0.38 -> 0.16294737 | R16: 0.8 | S16: 1.1 | T16: 0.8 | U16: 1.1 | V16: D | W16: 1
C17: output.bio_kerosene | D17: =D30 -> 0.15473684 | L17: Jet Fuel Output [MWh/MWh Total Input] | M17: 0.0147 | N17: 0.147 | O17: =N17*0.4/0.38 -> 0.15473684 | P17: =(O17+Q17)/2 -> 0.16440789 | Q17: =N17*0.45/0.38 -> 0.17407895 | R17: 0.8 | S17: 1.1 | T17: 0.8 | U17: 1.1 | V17: D | W17: 1
C18: output.biodiesel | D18: =D31 -> 0.10505263 | L18: Diesel Output [MWh/MWh Total Input] | M18: 0.0998 | N18: 0.0998 | O18: =N18*0.4/0.38 -> 0.10505263 | P18: =(O18+Q18)/2 -> 0.11161842 | Q18: =N18*0.45/0.38 -> 0.11818421 | R18: 0.8 | S18: 1.1 | T18: 0.8 | U18: 1.1 | V18: D | W18: 1
C19: output.bionaphtha | D19: =D32 -> 0.14484211 | L19: Electricity Output [MWh/MWh Total Input] | M19: 0.0117 | N19: 0.0117 | O19: 0.016 | P19: =(O19+Q19)/2 -> 0.018 | Q19: 0.02 | R19: 0.8 | S19: 1.1 | T19: 0.8 | U19: 1.1 | V19: D | W19: 1
C20: output.loss | D20: =E34 -> 0.59536842 | L20: Forced outage [%] | M20: 4 | N20: 4 | O20: 0 | P20: 0 | Q20: 0
C21: input.biogenic_waste | D21: =E37 -> 1 | L21: Planned outage [weeks per year] | M21: 2 | N21: 2 | O21: 2 | P21: 2 | Q21: 2
L22: Technical lifetime [years] | M22: 20 | N22: 25 | O22: 25 | P22: 25 | Q22: 25
C23: CCS | L23: Construction time [years] | M23: 2 | N23: 2 | O23: 2 | P23: 2 | Q23: 2
C24: ccs_investment | D24: =D64 -> 67820558 | E24: € | K24: Financial data
C25: variable_operation_and_maintenance_costs_for_ccs_per_full_load_hour | D25: =D63 -> 0 | E25: €/flh | L25: Specific investment [M€/MW Liquids/year] | M25: 4.6034632 | N25: 4.6034632 | O25: 4.1431169 | P25: 3.8478289 | Q25: 3.6827706 | R25: 0.75 | S25: 1.2 | T25: 0.75 | U25: 1.2 | V25: E, L | W25: 1, 6, 7, 8, 9
L26: - equipment [%] | M26: 75 | N26: 75 | O26: 75 | P26: 75 | Q26: 75
L27: - installation [%] | M27: 25 | N27: 25 | O27: 25 | P27: 25 | Q27: 25
C28: Feedstock in- and output | L28: Fixed O&M [M€/MW/year FT Liquids/year] | M28: 0.11048312 | N28: 0.11048312 | O28: 0.11048312 | P28: 0.10913842 | Q28: 0.11048312 | R28: 0.75 | S28: 1.2 | T28: 0.75 | U28: 1.2 | V28: L | W28: 1
C29: Output | D29: MJ/MJ | E29: corrected | L29: Variable O&M [€/MWh FT Liquids/year] | M29: 1.129941 | N29: 1.129941 | O29: 1.129941 | P29: 1.1310709 | Q29: 1.129941 | R29: 0.75 | S29: 1.2 | T29: 0.75 | U29: 1.2 | V29: L | W29: 1
C30: biokerosene | D30: =O17 -> 0.15473684 | E30: =D30 -> 0.15473684 | L30: Start up [M€/1,000 t FT Liquids/year] | M30: 0 | N30: 0 | O30: 0 | P30: 0 | Q30: 0 | V30: F
C31: biodiesel | D31: =O18 -> 0.10505263 | E31: =D31 -> 0.10505263 | K31: Technology-specific data
C32: bionaphtha | D32: =O16 -> 0.14484211 | E32: =D32 -> 0.14484211 | L32: Specific energy content [GJ/ton] FT Diesel | M32: 44 | N32: 44 | O32: 44 | P32: 44 | Q32: 44
C33: electricity | D33: =O19 -> 0.016 | E33: 0 | F33: assumption: very low electricity output is ignored and considered as loss | L33: Specific density [kg/l] or [ton/m3] | M33: 0.77 | N33: 0.77 | O33: 0.77 | P33: 0.77 | Q33: 0.77
C34: loss | D34: =1-SUM(D30:D33) -> 0.57936842 | E34: =1-SUM(E30:E33) -> 0.59536842 | L34: Specific investment [M€/1,000 t FT Liquids/year] | M34: 6.4935065 | N34: 6.4935065 | O34: 5.8441558 | P34: 5.5 | Q34: 5.1948052 | R34: 0.75 | S34: 1.2 | T34: 0.75 | U34: 1.2 | V34: E, L | W34: 1, 6, 7, 8, 9
C35: total | D35: =SUM(D30:D34) -> 1 | E35: =SUM(E30:E34) -> 1 | L35: - equipment [%] | M35: 75 | N35: 75 | O35: 75 | P35: 75 | Q35: 75
C36: Input | L36: - installation [%] | M36: 25 | N36: 25 | O36: 25 | P36: 25 | Q36: 25
C37: feedstock | D37: =M14 -> 1 | E37: =D37 -> 1 | L37: Fixed O&M [M€/1,000 t FT Liquids/year] | M37: 0.15584416 | N37: 0.15584416 | O37: 0.15584416 | P37: 0.156 | Q37: 0.15584416 | R37: 0.75 | S37: 1.2 | T37: 0.75 | U37: 1.2 | V37: L | W37: 1
L38: Variable O&M [M€/1,000 t FT Liquids/year] | M38: 0.012987013 | N38: 0.012987013 | O38: 0.012987013 | P38: 0.013 | Q38: 0.012987013 | R38: 0.75 | S38: 1.2 | T38: 0.75 | U38: 1.2 | V38: L | W38: 1
L39: Start up [M€/1,000 t FT Liquids/year] | M39: 0 | N39: 0 | O39: 0 | P39: 0 | Q39: 0 | V39: F
C40: Plant specs
C41: Based on DEA data, year 2030 is taken | K41: Notes:
C42: Plant size | D42: =O11*10^3 -> 100000 | E42: t FT liquids/y | L42: A. The plant size is assumed based on the proposed Velocys plant and the NREL nth plant.
C43: Plant size (production output) | D43: =O12 -> 150 | E43: MW | L43: A1. This value is the hourly rating and has been calculated as if the unit produces at capacity and was in operations 8,000 h/year
C44: Full load hours | D44: 8000 | E44: h | L44: B. Feedstock availability is likely to determine the maximum plant size.
C45: Technical lifetime | D45: =O22 -> 25 | E45: y | L45: C. The feedstock requirements could vary with efforts to improve the desired product selectivity.
C46: Construction time | D46: =O23 -> 2 | E46: y | L46: D. Over time the power available for export may increase due to improve thermal management in the plant.
C47: availability | D47: =1-O21/52 -> 0.96153846 | L47: E. There is a wide range of reported capital costs for the existing plants and a wide range in the cost of future plants.
L48: F. Start-up costs are included in the operating costs.
C49: Investment | D49: =O34*O11*10^6 -> 5.8441558e+08 | E49: € | L49: M €/k tonne is million euro per 1,000 tonnes
C50: Fixed O&M | D50: =O37*O11*10^6 -> 15584416 | E50: €/y
C51: Variable O&M | D51: =O38*O11*10^6 -> 1298701.3 | E51: €/y
C52: Variable O&M | D52: =D51/D44 -> 162.33766 | E52: €/flh
C54: CCS
C55: The biomass gassification process emits CO2 which is assumed to be captured
C57: CCS costs
C58: CCS costs are copied from energy_hydrogen_biomass_gasification_ccs which represents a similar process
C59: Correction for typical capacity of the technology needs to be done
C61: typical input capacity | D61: 481.66345 | E61: MW | F61: from energy_hydrogen_biomass_gasification_ccs
C62: ccs_investment | D62: 88119813 | E62: € | F62: from energy_hydrogen_biomass_gasification_ccs
C63: variable_operation_and_maintenance_costs_for_ccs_per_full_load_hour | D63: 0 | E63: €/flh | F63: from energy_hydrogen_biomass_gasification_ccs
C64: ccs_investment corrected | D64: =D62/D61*$D$6 -> 67820558 | E64: € | F64: ccs investment for this node
C67: Carbon in- and output
E70: syngas | I70: biokerosene
C71: biogenic waste | I71: biodiesel
I72: bionaphtha
F73: co2
F74: - emitted
F75: - captured
C78: Input | D78: Biogenic waste | E78: Unit | F78: CO2 stream | G78: Total | H78: Unit | J78: Output | K78: Biokerosene | L78: Biodiesel | M78: Bionaphtha | N78: Unit
C79: Energy input | D79: =E37 -> 1 | E79: MJ | F79: Carbon input | G79: =D81 -> 0.1 | H79: kg CO2 | J79: Energy output | K79: =E30 -> 0.15473684 | L79: =E31 -> 0.10505263 | M79: =E32 -> 0.14484211 | N79: MJ
C80: Emission factor | D80: 0.1 | E80: kg CO2/MJ | F80: Carbon output | G80: =SUM(K81:M81) -> 0.029690947 | H80: kg CO2 | I80: - | J80: Emission factor | K80: 0.0796 | L80: 0.0708 | M80: 0.0686 | N80: kg CO2/MJ
C81: Carbon input | D81: =D80*D79 -> 0.1 | E81: kg CO2 | F81: Carbon difference | G81: =G79-G80 -> 0.070309053 | H81: kg CO2 | J81: Carbon output | K81: =K80*K79 -> 0.012317053 | L81: =L80*L79 -> 0.0074377263 | M81: =M80*M79 -> 0.0099361684 | N81: kg CO2
C83: Emission factors taken from ETSource
F84: CO2 captured | G84: =G81*G88 -> 0.063278147 | H84: kg CO2
F85: CO2 emitted | G85: =G81*(1-G88) -> 0.0070309053 | H85: kg CO2
F86: CO2 total | G86: =G81 -> 0.070309053 | H86: kg CO2
F88: CO2 capture rate | G88: 0.9 | H88: taken from energy_hydrogen_biomass_gasification_ccs
C94: free_co2_factor | D94: =ROUND(G84/D81,6) -> 0.632781 | E94: - | F94: Share of CO2 captured in sum of (CO2 emitted, CO2 captured, CO2 in products)
C95: ccs_capture_rate | D95: 0.9 | E95: - | F95: Is the actual CO2 capture rate
C96: from_energy.conversion.biogenic_waste | D96: =ROUND(G86,6) -> 0.070309 | E96: kg CO2/MJ | F96: This is what goes to the molecule graph
